Workbook

Sheet Backlog
A1: Guest House Ops Hub — Product Backlog v1.0
A2: Source: discovery doc 14 (14-backlog.md). Delta-to-enterprise-quality; delivered baseline excluded. Cross-refs: doc 02 (FR/NFR), 05 (BR), 06 (GAP), 07 (RSK), 09 (Q).
A4: Epic | B4: Epic name | C4: Story ID | D4: As a… | E4: Story | F4: Acceptance criteria (Given/When/Then) | G4: References | H4: Priority | I4: Points | J4: Status
A5: E1 | B5: Production Safety & Operability | C5: US-101 | D5: MindBit ops | E5: Automated daily backups with an offsite copy per client DB | F5: GIVEN a client deployment WHEN the nightly job runs THEN a restorable snapshot exists offsite, retention 30d, and failure alerts ops. | G5: GAP-1, RSK-08 | H5: P0 | I5: 5 | J5: Proposed
A6: E1 | B6: Production Safety & Operability | C6: US-102 | D6: MindBit ops | E6: Documented, drilled restore runbook | F6: GIVEN a snapshot WHEN the runbook is executed on a scratch instance quarterly THEN RTO ≤ 4h is verified and logged. | G6: GAP-1 | H6: P0 | I6: 3 | J6: Proposed
A7: E1 | B7: Production Safety & Operability | C7: US-103 | D7: MindBit ops | E7: Error tracking + uptime checks on every deployment | F7: GIVEN an unhandled error or downtime WHEN it occurs THEN it appears in monitoring within 5 min tagged by client, and the UI shows an incident ID. | G7: GAP-17 | H7: P0 | I7: 5 | J7: Proposed
A8: E1 | B8: Production Safety & Operability | C8: US-104 | D8: Owner | E8: Sync health visible (iCal last-success, forwarder heartbeat, cron status) with staleness warnings | F8: GIVEN a feed not synced >12h WHEN I open Feeds/Today THEN a visible warning shows the age AND a push/alert fires (with E5). | G8: GAP-5, BR-AVL-05 | H8: P0 | I8: 5 | J8: Proposed
A9: E1 | B9: Production Safety & Operability | C9: US-105 | D9: MindBit ops | E9: Fleet dashboard: version, health, cron, backup status across clients | F9: GIVEN ≥2 deployments WHEN I open the dashboard THEN each shows version+health+last backup+last sync, red on breach. | G9: GAP-18 | H9: P1 | I9: 8 | J9: Proposed
A10: E2 | B10: Compliance: DPDP, Form C, GST | C10: US-201 | D10: Owner | E10: Pre-filled Form C artefact for a foreign guest, with submission tracking | F10: GIVEN a checked-in foreign guest WHEN I tap 'Form C' THEN a print-ready artefact with the 13 fields renders; a due-in-24h reminder persists until 'submitted' is ticked (audited). | G10: GAP-7, Q-LEG-02 | H10: P0 | I10: 5 | J10: Proposed
A11: E2 | B11: Compliance: DPDP, Form C, GST | C11: US-202 | D11: Owner | E11: Export and erase all data held about a guest (DPDP rights) | F11: GIVEN a guest requests erasure WHEN I trigger it THEN PII is removed/anonymised, bookings keep non-identifying financial integrity, and the action is audited. | G11: GAP-8 | H11: P0 | I11: 8 | J11: Proposed
A12: E2 | B12: Compliance: DPDP, Form C, GST | C12: US-203 | D12: MindBit | E12: Sane ID-scan retention default; purge provably runs | F12: GIVEN a new property WHEN created THEN idRetentionDays defaults (e.g. 180); purge logs deletions; owner notified of policy. | G12: BR-GST-05 | H12: P0 | I12: 3 | J12: Proposed
A13: E2 | B13: Compliance: DPDP, Form C, GST | C13: US-204 | D13: MindBit | E13: Breach-notification runbook + guest-facing privacy notice (incl. AI/US-cloud processing) | F13: Docs approved by counsel; notice linked in app. | G13: NFR-PRV-01/04 | H13: P0 | I13: 3 | J13: Proposed
A14: E2 | B14: Compliance: DPDP, Form C, GST | C14: US-205 | D14: Owner (GST) | E14: Invoices carry sequential per-FY numbers, GST lines, stored immutably | F14: GIVEN GSTIN configured WHEN an invoice is issued THEN an Invoice record exists with number series, tax lines per rate, immutable snapshot; reprint is identical. | G14: GAP-11, Q-FIN-02 | H14: P1 | I14: 8 | J14: Proposed
A15: E2 | B15: Compliance: DPDP, Form C, GST | C15: US-206 | D15: Guest | E15: Server-side PDF invoices | F15: Pixel-stable PDF, downloadable on a phone. | G15: GAP-11 | H15: P2 | I15: 5 | J15: Proposed
A16: E3 | B16: OTA Ingestion completeness | C16: US-301 | D16: Reception | E16: OTA modification/cancellation emails match the existing booking and guide the update | F16: GIVEN a booking with otaRef X WHEN a modification email for X is ingested THEN the pending item links to the booking, shows a diff, and 'Apply' updates via the normal conflict-checked path. | G16: GAP-2 | H16: P0 | I16: 8 | J16: Proposed
... A54: E9 | B54: Verification & spec-truth | C54: US-907 | D54: Engineering | E54: Guest merge tool with audit | F54: Merge preserves stays/LTV; irreversible warning; audited. | G54: GAP-19 | H54: P2 | I54: 5 | J54: Proposed

Sheet Epic Summary
A1: Epic Summary — counts & points derive from the Backlog sheet
A3: Epic | B3: Epic name | C3: Stories | D3: Points | E3: P0 stories | F3: P1 stories | G3: P2 stories | H3: P0 points
A4: E1 | B4: Production Safety & Operability | C4: =COUNTIF(Backlog!$A$5:$A$54,A4) -> 5 | D4: =SUMIF(Backlog!$A$5:$A$54,A4,Backlog!$I$5:$I$54) -> 26 | E4: =COUNTIFS(Backlog!$A$5:$A$54,A4,Backlog!$H$5:$H$54,"P0") -> 4 | F4: =COUNTIFS(Backlog!$A$5:$A$54,A4,Backlog!$H$5:$H$54,"P1") -> 1 | G4: =COUNTIFS(Backlog!$A$5:$A$54,A4,Backlog!$H$5:$H$54,"P2") -> 0 | H4: =SUMIFS(Backlog!$I$5:$I$54,Backlog!$A$5:$A$54,A4,Backlog!$H$5:$H$54,"P0") -> 18
A5: E2 | B5: Compliance: DPDP, Form C, GST | C5: =COUNTIF(Backlog!$A$5:$A$54,A5) -> 6 | D5: =SUMIF(Backlog!$A$5:$A$54,A5,Backlog!$I$5:$I$54) -> 32 | E5: =COUNTIFS(Backlog!$A$5:$A$54,A5,Backlog!$H$5:$H$54,"P0") -> 4 | F5: =COUNTIFS(Backlog!$A$5:$A$54,A5,Backlog!$H$5:$H$54,"P1") -> 1 | G5: =COUNTIFS(Backlog!$A$5:$A$54,A5,Backlog!$H$5:$H$54,"P2") -> 1 | H5: =SUMIFS(Backlog!$I$5:$I$54,Backlog!$A$5:$A$54,A5,Backlog!$H$5:$H$54,"P0") -> 19
A6: E3 | B6: OTA Ingestion completeness | C6: =COUNTIF(Backlog!$A$5:$A$54,A6) -> 6 | D6: =SUMIF(Backlog!$A$5:$A$54,A6,Backlog!$I$5:$I$54) -> 26 | E6: =COUNTIFS(Backlog!$A$5:$A$54,A6,Backlog!$H$5:$H$54,"P0") -> 1 | F6: =COUNTIFS(Backlog!$A$5:$A$54,A6,Backlog!$H$5:$H$54,"P1") -> 3 | G6: =COUNTIFS(Backlog!$A$5:$A$54,A6,Backlog!$H$5:$H$54,"P2") -> 2 | H6: =SUMIFS(Backlog!$I$5:$I$54,Backlog!$A$5:$A$54,A6,Backlog!$H$5:$H$54,"P0") -> 8
A7: E4 | B7: Money correctness | C7: =COUNTIF(Backlog!$A$5:$A$54,A7) -> 7 | D7: =SUMIF(Backlog!$A$5:$A$54,A7,Backlog!$I$5:$I$54) -> 40 | E7: =COUNTIFS(Backlog!$A$5:$A$54,A7,Backlog!$H$5:$H$54,"P0") -> 2 | F7: =COUNTIFS(Backlog!$A$5:$A$54,A7,Backlog!$H$5:$H$54,"P1") -> 4 | G7: =COUNTIFS(Backlog!$A$5:$A$54,A7,Backlog!$H$5:$H$54,"P2") -> 1 | H7: =SUMIFS(Backlog!$I$5:$I$54,Backlog!$A$5:$A$54,A7,Backlog!$H$5:$H$54,"P0") -> 13
A8: E5 | B8: Notifications & Messaging activation | C8: =COUNTIF(Backlog!$A$5:$A$54,A8) -> 4 | D8: =SUMIF(Backlog!$A$5:$A$54,A8,Backlog!$I$5:$I$54) -> 21 | E8: =COUNTIFS(Backlog!$A$5:$A$54,A8,Backlog!$H$5:$H$54,"P0") -> 1 | F8: =COUNTIFS(Backlog!$A$5:$A$54,A8,Backlog!$H$5:$H$54,"P1") -> 2 | G8: =COUNTIFS(Backlog!$A$5:$A$54,A8,Backlog!$H$5:$H$54,"P2") -> 1 | H8: =SUMIFS(Backlog!$I$5:$I$54,Backlog!$A$5:$A$54,A8,Backlog!$H$5:$H$54,"P0") -> 5
A9: E6 | B9: Auth & access hardening | C9: =COUNTIF(Backlog!$A$5:$A$54,A9) -> 6 | D9: =SUMIF(Backlog!$A$5:$A$54,A9,Backlog!$I$5:$I$54) -> 18 | E9: =COUNTIFS(Backlog!$A$5:$A$54,A9,Backlog!$H$5:$H$54,"P0") -> 2 | F9: =COUNTIFS(Backlog!$A$5:$A$54,A9,Backlog!$H$5:$H$54,"P1") -> 4 | G9: =COUNTIFS(Backlog!$A$5:$A$54,A9,Backlog!$H$5:$H$54,"P2") -> 0 | H9: =SUMIFS(Backlog!$I$5:$I$54,Backlog!$A$5:$A$54,A9,Backlog!$H$5:$H$54,"P0") -> 8
A10: E7 | B10: Fleet & onboarding | C10: =COUNTIF(Backlog!$A$5:$A$54,A10) -> 6 | D10: =SUMIF(Backlog!$A$5:$A$54,A10,Backlog!$I$5:$I$54) -> 28 | E10: =COUNTIFS(Backlog!$A$5:$A$54,A10,Backlog!$H$5:$H$54,"P0") -> 0 | F10: =COUNTIFS(Backlog!$A$5:$A$54,A10,Backlog!$H$5:$H$54,"P1") -> 4 | G10: =COUNTIFS(Backlog!$A$5:$A$54,A10,Backlog!$H$5:$H$54,"P2") -> 2 | H10: =SUMIFS(Backlog!$I$5:$I$54,Backlog!$A$5:$A$54,A10,Backlog!$H$5:$H$54,"P0") -> 0
A11: E8 | B11: Localization & accessibility | C11: =COUNTIF(Backlog!$A$5:$A$54,A11) -> 3 | D11: =SUMIF(Backlog!$A$5:$A$54,A11,Backlog!$I$5:$I$54) -> 21 | E11: =COUNTIFS(Backlog!$A$5:$A$54,A11,Backlog!$H$5:$H$54,"P0") -> 0 | F11: =COUNTIFS(Backlog!$A$5:$A$54,A11,Backlog!$H$5:$H$54,"P1") -> 1 | G11: =COUNTIFS(Backlog!$A$5:$A$54,A11,Backlog!$H$5:$H$54,"P2") -> 2 | H11: =SUMIFS(Backlog!$I$5:$I$54,Backlog!$A$5:$A$54,A11,Backlog!$H$5:$H$54,"P0") -> 0
A12: E9 | B12: Verification & spec-truth | C12: =COUNTIF(Backlog!$A$5:$A$54,A12) -> 7 | D12: =SUMIF(Backlog!$A$5:$A$54,A12,Backlog!$I$5:$I$54) -> 22 | E12: =COUNTIFS(Backlog!$A$5:$A$54,A12,Backlog!$H$5:$H$54,"P0") -> 3 | F12: =COUNTIFS(Backlog!$A$5:$A$54,A12,Backlog!$H$5:$H$54,"P1") -> 2 | G12: =COUNTIFS(Backlog!$A$5:$A$54,A12,Backlog!$H$5:$H$54,"P2") -> 2 | H12: =SUMIFS(Backlog!$I$5:$I$54,Backlog!$A$5:$A$54,A12,Backlog!$H$5:$H$54,"P0") -> 10
B13: TOTAL | C13: =SUM(C4:C12) -> 50 | D13: =SUM(D4:D12) -> 234 | E13: =SUM(E4:E12) -> 17 | F13: =SUM(F4:F12) -> 22 | G13: =SUM(G4:G12) -> 11 | H13: =SUM(H4:H12) -> 81

Sheet DoR · DoD · Legend
A1: Working agreements
A3: Definition of Ready | B3: Open questions referenced by the story are answered; acceptance criteria agreed; test data identified; any touch to the GiST-constraint/migration machinery flagged for senior review.
A4: Definition of Done | B4: Code + tests (unit; route-level where API changes) green in CI; migration via db:migrate:new only; docs updated (USER-GUIDE/ARCHITECTURE); audit/RBAC respected; deployed to a pilot-mirror environment; demoed.
A5: Priority P0 | B5: Production-safety / legal — gate for scaling past first pilots (Roadmap Phase 1).
A6: Priority P1 | B6: Scale & commercial — grant Q2/Q3 alignment (Roadmap Phase 2).
A7: Priority P2 | B7: Quality & experience — Roadmap Phase 3.
A8: Status values | B8: Proposed → Ready → In progress → Done (set 'Proposed' by default; update during grooming).
A9: Import note | B9: Backlog sheet columns map 1:1 to Jira CSV import (Epic Link, Summary=Story, Description=AC, Labels=References, Priority, Story Points).
